treemancer/__init__.py
treemancer/__main__.py
treemancer/cli.py
treemancer/creator.py
treemancer/models.py
treemancer/languages/__init__.py
treemancer/languages/diagram/__init__.py
treemancer/languages/diagram/lexer.py
treemancer/languages/diagram/parser.py
treemancer/languages/diagram/tokens.py
treemancer/languages/structural/__init__.py
treemancer/languages/structural/lexer.py
treemancer/languages/structural/parser.py
treemancer/languages/structural/tokens.py
treemancer/parsers/__init__.py
treemancer/parsers/tree_parser.py
treemancer/ui/__init__.py
treemancer/ui/components.py
treemancer/ui/styles.py
treemancer-0.2.0.dist-info/METADATA
treemancer-0.2.0.dist-info/WHEEL
treemancer-0.2.0.dist-info/entry_points.txt
treemancer-0.2.0.dist-info/licenses/LICENSE
treemancer-0.2.0.dist-info/RECORD
