Metadata-Version: 2.4
Name: treemancer
Version: 0.2.0
Summary: A magical CLI tool to create directory structures from tree diagrams and custom structural language definitions
Project-URL: Homepage, https://github.com/ericmiguel/treemancer
Project-URL: Documentation, https://github.com/ericmiguel/treemancer#readme
Project-URL: Repository, https://github.com/ericmiguel/treemancer.git
Project-URL: Bug Tracker, https://github.com/ericmiguel/treemancer/issues
Project-URL: Changelog, https://github.com/ericmiguel/treemancer/blob/main/CHANGELOG.md
Author-email: Eric Miguel <eric.mrib@gmail.com>
Maintainer-email: Eric Miguel <eric.mrib@gmail.com>
License:                     GNU AFFERO GENERAL PUBLIC LICENSE
License-File: LICENSE
Keywords: cli,directory,file-structure,project-setup,scaffolding,tree
Classifier: Development Status :: 4 - Beta
Classifier: Environment :: Console
Classifier: Intended Audience :: Developers
Classifier: License :: OSI Approved :: GNU Affero General Public License v3
Classifier: Operating System :: OS Independent
Classifier: Programming Language :: Python :: 3
Classifier: Programming Language :: Python :: 3 :: Only
Classifier: Programming Language :: Python :: 3.13
Classifier: Topic :: Software Development :: Code Generators
Classifier: Topic :: System :: Filesystems
Classifier: Topic :: Utilities
Classifier: Typing :: Typed
Requires-Python: >=3.12
Requires-Dist: pyyaml>=6.0.2
Requires-Dist: rich>=13.0.0
Requires-Dist: typer>=0.9.0
